{
  "name": "awesome-azure-landing-zones",
  "description": "AI skills and agents for the Microsoft Cloud Adoption Framework (CAF) and Azure Landing Zones (ALZ): the eight design areas, the ALZ Accelerator, subscription/landing-zone vending, governance and policy, and networking and connectivity.",
  "version": "0.1.0",
  "author": {
    "name": "Jan Egil Ring",
    "url": "https://github.com/janegilring"
  },
  "homepage": "https://github.com/janegilring/awesome-azure-landing-zones",
  "repository": "https://github.com/janegilring/awesome-azure-landing-zones",
  "license": "MIT",
  "keywords": ["azure", "landing-zones", "caf", "alz", "governance", "networking", "vending"],
  "category": "Azure",
  "agents": "agents/",
  "skills": "skills/"
}
